{
  "section1": {"files": [
    {
      "type": "animation",
      "key": "animations",
      "url": "assets/atlas/animations.json"
    },
    {
      "type": "multiatlas",
      "key": "character",
      "url": "assets/atlas/character.json",
      "path": "assets/atlas"
    },
    {
      "type": "sceneFile",
      "key": "Level",
      "url": "assets/scene/Level.js"
    },
    {
      "type": "sceneFile",
      "key": "Start",
      "url": "assets/scene/Start.js"
    },
    {
      "type": "sceneFile",
      "key": "Results",
      "url": "assets/scene/Results.js"
    },
    {
      "type": "script",
      "key": "ship",
      "url": "assets/prefabs/ship.js"
    },
    {
      "type": "script",
      "key": "waypoint",
      "url": "assets/prefabs/waypoint.js"
    },
    {
      "type": "image",
      "key": "mountains-back",
      "url": "assets/mountains-back.png",
      "normalMap": ""
    },
    {
      "type": "image",
      "key": "mountains-mid1",
      "url": "assets/mountains-mid1.png",
      "normalMap": ""
    },
    {
      "type": "image",
      "key": "mountains-mid2",
      "url": "assets/mountains-mid2.png",
      "normalMap": ""
    },
    {
      "type": "image",
      "key": "title",
      "url": "assets/title.png",
      "normalMap": ""
    },
    {
      "type": "script",
      "key": "FadePipeline",
      "url": "assets/prefabs/FadePipeline.js"
    },
    {
      "type": "script",
      "key": "FadeRenderTexture",
      "url": "assets/prefabs/FadeRenderTexture.js"
    },
    {
      "type": "atlas",
      "key": "flares",
      "textureURL": "assets/atlas/flares.png",
      "atlasURL": "assets/atlas/flares.json",
      "format": "TEXTURE_ATLAS_JSON_HASH"
    },
    {
      "type": "image",
      "key": "potogold",
      "url": "assets/potogoldv2.png",
      "normalMap": ""
    },
    {
      "type": "image",
      "key": "leftthrust",
      "url": "assets/letter_s.png",
      "normalMap": ""
    },
    {
      "type": "image",
      "key": "rightthrust",
      "url": "assets/letter_k.png",
      "normalMap": ""
    },
    {
      "type": "image",
      "key": "leftreversethrust",
      "url": "assets/letter_w.png",
      "normalMap": ""
    },
    {
      "type": "image",
      "key": "rightreversethrust",
      "url": "assets/letter_o.png",
      "normalMap": ""
    },
    {
      "type": "image",
      "key": "gold",
      "url": "assets/gold.png",
      "normalMap": ""
    }
  ]},
  "meta": {
    "generated": "1554162759970",
    "app": "Phaser Editor",
    "url": "https://phasereditor2d.com",
    "version": "1.0",
    "copyright": "Arian Fornaris (c) 2015,2018"
  }
}